dragon_env/__init__.py
dragon_env/core.py
dragon_env-0.1.0.dist-info/licenses/LICENSE
dragon_env-0.1.0.dist-info/METADATA
dragon_env-0.1.0.dist-info/WHEEL
dragon_env-0.1.0.dist-info/top_level.txt
dragon_env-0.1.0.dist-info/RECORD
